zenpulse_scheduler/__init__.py
zenpulse_scheduler/admin.py
zenpulse_scheduler/apps.py
zenpulse_scheduler/engine.py
zenpulse_scheduler/listeners.py
zenpulse_scheduler/locks.py
zenpulse_scheduler/models.py
zenpulse_scheduler/registry.py
zenpulse_scheduler/sync.py
zenpulse_scheduler/triggers.py
zenpulse_scheduler/management/commands/run_zenpulse_scheduler.py
zenpulse_scheduler/migrations/__init__.py
zenpulse_scheduler-0.1.1.dist-info/METADATA
zenpulse_scheduler-0.1.1.dist-info/WHEEL
zenpulse_scheduler-0.1.1.dist-info/top_level.txt
zenpulse_scheduler-0.1.1.dist-info/RECORD
