Metadata-Version: 2.4
Name: zenpulse_scheduler
Version: 0.1.1
Summary: A DB-driven APScheduler for Django
Classifier: Framework :: Django
Classifier: Programming Language :: Python :: 3
Requires-Python: >=3.8
Requires-Dist: django>=3.2
Requires-Dist: apscheduler>=3.6.3
